{
  "triton-square": {
    "name": "Triton Square",
    "url": "https://www.tritonsquare.com/availability-map/",
    "status": "live",
    "pricing": [],
    "availability": null,
    "error": null,
    "raw": "Press Option+1 for screen-reader mode, Option+0 to cancel\nAccessibility Screen-Reader Guide, Feedback, and Issue Reporting | New window\nHOME\nAPARTMENTS\nAVAILABILITY\nAMENITIES\nGALLERY\nNEIGHBORHOOD\nFAQS\nDIRECTIONS\nRESIDENTS\nLEASE NOW\n \nHOME APARTMENTS AVAILABILITY AMENITIES GALLERY NEIGHBORHOOD FAQS DIRECTIONS RESIDENTS LEASE NOW\nHOME APARTMENTS AVAILABILITY AMENITIES GALLERY NEIGHBORHOOD FAQS DIRECTIONS RESIDENTS LEASE NOW\n\nTAKE THE NEXT STEP\n\n1 Triton Square, Groton, CT 06340\n\nMonday: 8:00 AM to 5:00 PM\nTuesday: 8:00 AM to 6:00 PM\nWednesday:8:00 AM to 5:00 PM\nThursday: 8:00 AM to 6:00 PM\nFriday: 8:00 AM to 5:00 PM\nSaturday: 10:00 AM to 4:00 PM\nSunday: 10:00 AM to 4:00 PM\n\n860-222-5626\n\n \nHOME APARTMENTS AMENITIES NEIGHBORHOOD DIRECTIONS\nPrivacy Policy. Terms of Use.\nWebsite by Resident360  "
  },
  "pleasant-valley": {
    "name": "Pleasant Valley",
    "url": "https://www.pleasantvalley-apts.com/apartments/ct/groton/floor-plans",
    "status": "live",
    "pricing": [
      "$1,920",
      "$2,135",
      "$2,445"
    ],
    "availability": null,
    "error": null,
    "raw": "Skip to Main Content\n\n700 Pleasant Valley Rd N, Groton, CT 06340\n\nMENU\n959-949-1109\nRESIDENTS\nAPPLY NOW\nFLOOR PLANS\nPHOTO GALLERY\nVIRTUAL TOUR\nAMENITIES\nPET FRIENDLY\nESA/SA APPLICATION\nNEIGHBORHOOD\nCONTACT US\nSCHEDULE A TOUR\nREVIEWS\nMAP + DIRECTIONS\n\nFLOOR PLANS\n\nSTUDIO, 1 & 2 BEDROOM APARTMENTS\n\nAt Pleasant Valley Apartments, we know how important it is for your home to fit you. Our apartments come in a variety of layouts, so you can pick the floor plan that works best for you. Additionally, every residence comes standard with perks like a private outdoor space and Asian-plank flooring. Whether you’re cuddling with your pet, hosting a dinner or game night with friends, or just relaxing after a long day, Pleasant Valley Apartments is the perfect place for you.\n\nCHOOSE YOUR FLOOR PLAN\n\nAvailability:\n\nPreferred Move-In Date\nevent\n\nFilter By:\n\nrefresh\nReset Filters\nBedrooms\nkeyboard_arrow_down\nBathrooms\nkeyboard_arrow_down\nattach_money\nMin Price\nattach_money\nMax Price\nMore Filters\nadd\n\nStyle 1\n\nStudio\n1 Bath\n623 Sq.Ft\n\nFrom $1,920*\n\nadd_circle_outline\nAMENITIES\n\n* Estimated price does not include non-optional fees.\n\nVIEW 3 APARTMENTS\n\nStyle 2\n\n1 Bed\n1 Bath\n831 Sq.Ft\n\nFrom $2,135*\n\nadd_circle_outline\nAMENITIES\n\n* Estimated price does not include non-optional fees.\n\nVIEW 4 APARTMENTS\n\nStyle 3\n\n2 Beds\n2 Baths\n1,023 Sq.Ft\n\nFrom $2,445*\n\nadd_circle_outline\nAMENITIES\n\n* Estimated price does not include non-optional fees.\n\nVIEW 1 APARTMENT\nchevron_left\nchevron_right\nView All Floor Plans\nEVERYTHING YOU NEED IS HERE\n\nNo matter which floor plan you choose at Pleasant Valley Apartments, enjoy a tastefully styled, brightly lit home with plenty of space in a comfortable suburban setting.\n\nEvery day, appreciate your new home’s features that just make life easier, like an in-home washer and dryer, a private outdoor space, and upgraded finishes throughout.\n\nThis is where you want to be in Groton, Connecticut.\n\nYOUR LUXURY OASIS\n\nAPPLY NOW\nPleasant Valley Apartments\n\n700 Pleasant Valley Rd N Groton, CT 06340\n\n959-949-1109\n\nEmail Us\n\n(21 reviews)\nOffice Hours\nMonday - Thursday: 9:00am - 5:00pm\nFriday: 8:00am - 4:00pm\nSaturday - Sunday: Closed\n\nPrivacy Policy\nAccessibility Statement\n\nCopyright © 2026 Pleasant Valley Apartments\n\nEqual Opportunity Housing\nHandicap Friendly\n\nBy clicking “Accept All Cookies”, you agree to the storing of cookies on your device to enhance site navigation, analyze site usage, and assist in our marketing efforts.\nAccept All Cookies\nCookies Settings"
  },
  "harbor-heights-enclave": {
    "name": "Harbor Heights Enclave",
    "url": "https://www.hmystic.com/enclave/floor-plans-enclave",
    "status": "live",
    "pricing": [],
    "availability": null,
    "error": null,
    "raw": "HOME\nENCLAVE\nBEACON\nGALLERY\nLOCATION\nBROCHURE\nRESIDENTS\nLEASE NOW\nFURNISH\nCONTACT\nENCLAVE FLOOR PLANS\nBRAND NEW MYSTIC APARTMENT HOMES | NOW LEASING FOR FALL 2024\n-CONTACT OUR OFFICE TO SCHEDULE A TOUR & SUBMIT AN APPLICATION-\nMontauk\n699\nSq Ft\n1 Bedroom / 1 Bath\nThe Cape\n742\nSq Ft\n1 Bedroom / 1 Bath\nFishers Island\n835\nSq Ft\n1 Bedroom / 1 Bath / Den\nWatch Hill Penthouse | Loft\n869\nSq Ft\n1 Bedroom / 1 Bath / Mainsail Penthouse Loft\nBlock Island Penthouse | Loft\n959\nSq Ft\n1 Bedroom / 1 Bath / Den / Mainsail Penthouse Loft\nMystic\n1045\nSq Ft\n2 Bedroom / 2 Bath\nNantucket\n1046\nSq Ft\n2 Bedroom / 2 Bath\nNewport Penthouse | Loft\n1184\nSq Ft\n2 Bedroom / 2 Bath / Mainsail Penthouse Loft\nThe Vineyard\n1323\nSq Ft\n2 Bedroom / 2 Bath Corner\nSouthhampton\n1447\nSq Ft\n2 Bedroom / 2 Bath / Den Corner\nShelter Island\n1601\nSq Ft\n3 Bedroom / 2 Bath Corner\nSag Harbor\n1638\nSq Ft\n3 Bedroom / 2 Bath Corner\nAll photos, renderings, floor plans, maps, and images used herein are artists' conceptions; dimensions, square footage, and features herein are not to scale but for illustrative purposes. All dimensions are estimates only and may not be exact measurements. Floor plans are subject to change. All pricing and availability are subject to change. The information is to be used as a point of reference and not a binding agreement.\n\nLET YOUR VOYAGE BEGIN. LEASE NOW.\nSEE AVAILABILITY\nHARBOR HEIGHTS MYSTIC\nWhether you’re a young professional, downsizing, or an empty nester, Harbor Heights modern one, two & three bedroom residences will welcome you in to the next phase of your life. Come experience downtown Mystics newest lifestyle destination. Move to Sea.\n\n\nTRIO PROPERTIES\nBuilding value through our management expertise. Leading properties in their best direction.\n\nSee why TRIO Properties is an award-winning Property Management Company, year-after-year.\nADDRESS\n50 Perkins Farm Drive\nMystic, CT 06355\n(860) 764-2667\nMon-Fri 9-5:30, Sat By Appointment, Sun Closed\nGALLERY\n© 2025 Harbor Heights Mystic. All rights reserved.\nSite by BRIO MKTG"
  },
  "harbor-heights-beacon": {
    "name": "Harbor Heights Beacon",
    "url": "https://www.hmystic.com/beacon/floor-plans-beacon",
    "status": "live",
    "pricing": [],
    "availability": null,
    "error": null,
    "raw": "HOME\nENCLAVE\nBEACON\nGALLERY\nLOCATION\nBROCHURE\nRESIDENTS\nLEASE NOW\nFURNISH\nCONTACT\nBEACON FLOOR PLANS\n1, 2, & 3 BEDROOMS | LUXURY MYSTIC APARTMENTS | LEASE TODAY \nBroad Reach\n665\nSq Ft\n1 Bath / 1 Bedroom\nCarpe Diem\n723\nSq Ft\n1 Bath / 1 Bedroom\nDolce Vita\n813\nSq Ft\n1 Bath / 1 Bedroom / Den\nEclipse\n922\nSq Ft\n1 Bath / 1 Bedroom / Den\nGypsea\n1025\nSq Ft\n2 Bath / 2 Bedroom\nOdyssey\n1191\nSq Ft\n2 Bath / 2 Bedroom\nReel Escape\n1282\nSq Ft\n2 Bath / 2 Bedroom / Den\nThe Pearl\n1309\nSq Ft\n2 Bath / 2 Bedroom\nZephyr\n1436\nSq Ft\n2 Bath / 2 Bedroom / Den\nAll photos, renderings, floor plans, maps, and images used herein are artists' conceptions; dimensions, square footage, and features herein are not to scale but for illustrative purposes. All dimensions are estimates only and may not be exact measurements. Floor plans are subject to change. All pricing and availability are subject to change. The information is to be used as a point of reference and not a binding agreement.\n\nLET YOUR VOYAGE BEGIN. LEASE NOW.\nSEE AVAILABILITY\nHARBOR HEIGHTS MYSTIC\nWhether you’re a young professional, downsizing, or an empty nester, Harbor Heights modern one, two & three bedroom residences will welcome you in to the next phase of your life. Come experience downtown Mystics newest lifestyle destination. Move to Sea.\n\n\nTRIO PROPERTIES\nBuilding value through our management expertise. Leading properties in their best direction.\n\nSee why TRIO Properties is an award-winning Property Management Company, year-after-year.\nADDRESS\n50 Perkins Farm Drive\nMystic, CT 06355\n(860) 764-2667\nMon-Fri 9-5:30, Sat By Appointment, Sun Closed\nGALLERY\n© 2025 Harbor Heights Mystic. All rights reserved.\nSite by BRIO MKTG"
  },
  "waterford-woods": {
    "name": "Waterford Woods",
    "url": "https://www.waterfordwoods.com/availability",
    "status": "live",
    "pricing": [],
    "availability": null,
    "error": null,
    "raw": "Skip to Main Content\n\nHOME\n\nAPARTMENTS\n\nAVAILABILITY\n\nAMENITIES\n\nSHORT TERM RENTAL\n\nNEIGHBORHOOD\n\nMore\n\nAVAILABILITY\nCONTACT\n\n \n\n394 Willets Ave. Waterford, CT 06385\n\nWaterfordwoodsapt@gmail.com\n\n860-772-2253\n\n© 2023 Copyright. | All Rights Reserved. | WaterFord Woods, LLC\n\nSUBMIT"
  },
  "groton-estates": {
    "name": "Groton Estates",
    "url": "https://grotonestates.com/floor-plans/",
    "status": "live",
    "pricing": [
      "$1,775",
      "$2,065"
    ],
    "availability": "10 UNITS AVAIL",
    "error": null,
    "raw": "Press Option+1 for screen-reader mode, Option+0 to cancel\nAccessibility Screen-Reader Guide, Feedback, and Issue Reporting | New window\n(860) 406-5935\nFLOOR PLANS\nSCHEDULE TOUR \nRESIDENT PORTAL \nFLOOR PLANS\nINTERACTIVE MAP\nALL\n1 BEDROOM\n2 BEDROOM\n3 BEDROOM\n1BR 1BA\n\n1 Bedroom | 1 Bathroom | 639 Sq. Ft.\n\nCall for Pricing\n\nVIEW FLOOR PLAN\n2BR 1BA\n\n2 Bedrooms | 1 Bathroom | 786 Sq. Ft.\n\n$1,775.00 - $2,065.00 /mo *\n\n$1,775.00 - $2,065.00 Base Rent\n\n10 UNITS AVAILABLE\n3BR 1BA\n\n3 Bedrooms | 1 Bathroom | 983 Sq. Ft.\n\nCall for Pricing\n\nVIEW FLOOR PLAN\nHOME\nAMENITIES\nGALLERY\nNEIGHBORHOOD\nFLOOR PLANS\nAPPLY NOW\nSCHEDULE A TOUR\nRESIDENTS\nCONTACT\n\n\n260 SHENNECOSSETT RD\nGROTON, CT 06340\n\n(860) 406-5935\n\n-\n\nMONDAY - FRIDAY: 9:00AM - 5:00PM\nSATURDAY: BY APPOINTMENT ONLY\nSUNDAY: CLOSED\n\n\n\n\n\n\n\n\n\nPRIVACY POLICY TERMS ALL RIGHTS RESERVED\nWebsite by Resident360"
  },
  "chester-place": {
    "name": "Chester Place",
    "url": "https://www.b7properties.com/chester-place",
    "status": "live",
    "pricing": [
      "$1,925"
    ],
    "availability": null,
    "error": null,
    "raw": "Skip to Main Content\n\nHome\n\nAbout b7\n\nFor Investors\n\nAvailable Properties\n\nb7 Team\n\nContact\n\n401-396-9777\n\nChester Place\nNo up-front security deposit!\nApply Now\nCall/Text to Tour\nReserve a Showing\nEmail to Tour\n\n46 Hynes Ave, Groton, CT, 06340\n\nKitchen - 1-Bedroom\n\n2/17\nProperty Floor Plans\n\n1-BEDROOM, 1-BATH\n\nClick below to see 3-D Tour\n\nSee 3D Tour\nSee Video Tour\n\n1-Bedroom, 1-Bath\n(608 sq. ft.) - $1,925/month\n\nProperty Description\n\n \n\nWelcome to Chester Place, a newly and fully renovated pet-friendly community offering modern luxury living. The Chester Place is comprised of 6 two-story buildings featuring one-bedroom apartments. \n\n​\n\nEach apartment is designed with an open-concept floor plan and contemporary finishes, including stainless steel appliances, granite countertops, shaker-style kitchen cabinets, engineered hardwood flooring, and recessed lighting. Enjoy the convenience of an in-unit washer and dryer and in-wall A/C units. Ample outdoor lighting and a security system have been added to enhance safety. \n\n​\n\nChester Place is a convenient five-minute commute to local employers and just 2 miles from Interstate 95. As part of our comprehensive living experience, the monthly community fee of $99 covers essential services such as full-service WiFi, trash removal, Renters Insurance, Resident reward program, and credit building to make it easier to manage your monthly expenses.\n\n​\n\nOur attentive, full-time on-site team and convenient online resident portal ensure that maintenance requests are handled promptly and effectively, with the added convenience of easy online payments.\n\n​\n\nWe hope to have you join us soon!\n\nProperty Details\nContact:\n\nMartha\n\n(Property Manager)\n\nmartha@b7properties.com\n\n(860) 400-2050\n\n​\n\nParking:\n\nFree off-street parking. 1 assigned spot included.\n\nCommunity Fee:\n\n$99/month\n\nIncludes WiFi, Security Deposit, Water, Sewer, Trash Removal, Renters Insurance, Resident Rewards Program & Credit Building \n\nFeatures:\n\nSurveillance System, Grilling Area, & Air Conditioning\n\nPet Fees:\n\nRegistration Fee: $250\n\nDog Fee: $40/month\n\nCat Fee: $30/month\n\nUp-Front Costs:\n\nFirst Month's Rent & Fees, No up-front deposit, & Proof of utilities required before move-in\n\nThank you for visiting the Chester Place property page!\nApply Now\nReserve a Showing\nCall/Text to Tour\nEmail to Tour\nProperty Video\n\n© 2025 b7 Properties.\n\nb7@b7properties.com\n\n401-396-9777 "
  },
  "emerson-place": {
    "name": "Emerson Place",
    "url": "https://www.b7properties.com/emerson",
    "status": "live",
    "pricing": [
      "$1,975",
      "$1,995",
      "$2,445"
    ],
    "availability": null,
    "error": null,
    "raw": "Skip to Main Content\n\nHome\n\nAbout b7\n\nFor Investors\n\nAvailable Properties\n\nb7 Team\n\nContact\n\n401-396-9777\n\nEmerson Place\nNo up-front security deposit!\nApply Now\nReserve a Showing\nCall/Text to Tour\nEmail to Tour\n\n233-245 Benham Road, Groton, CT, 06340\n\nKitchen - 2-Bedrooms\n\n2/16\nProperty Floor Plans\n\n1-BEDROOM, 1-BATH\n\nClick below to see 3-D Tour and Video Tour\n\nSee Video Tour\nSee 3D Tour\n\n1-Bedroom, 1-Bath\n(678 sq. ft.) - $1,975/month\n\n1-BEDROOM, 1-BATH CORNER\n\nClick below to see 3-D Tour and Video Tour\n\nSee Video Tour\nSee 3D Tour\n\n1-Bedroom, 1-Bath Corner\n(738 sq. ft.) - $1,995/month\n\nProperty Description\n\nWelcome to Emerson Place, a newly and fully renovated pet-friendly community offering modern luxury. Emerson Place is comprised of three two-story buildings featuring one and two-bedroom apartments, as well as outdoor amenities such as a pet play area and a community grilling and patio area. \n\n \n\nEach apartment is designed with an open-concept floor plan and contemporary finishes, including stainless steel appliances, granite countertops, shaker-style kitchen cabinets, engineered hardwood flooring, and recessed lighting. Enjoy the convenience of an in-unit washer and dryer and an in-wall A/C unit. Ample outdoor lighting and a security system have been added to enhance safety. \n\n \n\nEmerson Place is conveniently located just 2 miles from Interstate 95 and downtown Groton. As part of our comprehensive living experience, the monthly community fee of $99 covers essential services such as full-service WiFi, trash removal, Renters Insurance, Resident reward program, and credit building to make it easier to manage your monthly expenses.\n\n \n\nOur attentive, full-time on-site team and convenient online resident portal ensure that maintenance requests are handled promptly and effectively, with the added convenience of easy online payments.\n\n \n\nWe hope to have you join us soon!\n\nProperty Details\nContact:\n\nMartha\n\n(Property Manager)\n\nmartha@b7properties.com\n\n(860) 400-2050\n\nFeatures:\n\nAir Conditioning, Dog Play Area, Washer & Dryer, Surveillance System, & Grilling Area Included!\n\nParking:\n\nOne FREE assigned \n\nparking spot\n\nAdditional surface lot parking free\n\nPet Fees:\n\nRegistration Fee: $250\n\nDog Fee: $40/month\n\nCat Fee: $30/month\n\nCommunity Fee:\n\n$99/month\n\nIncludes Heat, Hot Water, Gas, Water Sewer, Trash Removal, WiFi, Renters Insurance, Resident Rewards Program & Credit Building \n\nUp-Front Costs:\n\nFirst month’s rent upon signing lease, and no up-front security deposit.\n\nThank you for visiting the Emerson Place property page!\nApply Now\nReserve a Showing\nCall/Text to Tour\nEmail to Tour\nProperty Video\n\n2-BEDROOM, 1-BATH\n\nClick below to see 3-D Tour and Video Tour\n\nSee Video Tour\nSee 3D Tour\n\n2-Bedroom, 1-Bath\n(925 sq. ft.) - $2,445/month\n\n© 2025 b7 Properties.\n\nb7@b7properties.com\n\n401-396-9777 "
  },
  "the-ledges": {
    "name": "The Ledges",
    "url": "https://www.theledgesapartments.com/floorplans",
    "status": "HTTP_403",
    "pricing": [],
    "availability": null,
    "error": null,
    "raw": ""
  },
  "gull-harbor": {
    "name": "Gull Harbor",
    "url": "https://gullharborct.com/floorplans",
    "status": "HTTP_404",
    "pricing": [],
    "availability": null,
    "error": null,
    "raw": ""
  }
}